gene_outlier_detection/__init__.py
gene_outlier_detection/cli.py
gene_outlier_detection/lib.py
gene_outlier_detection/main.py
gene_outlier_detection/meta_runner.py
gene_outlier_detection-1.0.dist-info/entry_points.txt
gene_outlier_detection-1.0.dist-info/WHEEL
gene_outlier_detection-1.0.dist-info/METADATA
gene_outlier_detection-1.0.dist-info/RECORD
