Metadata-Version: 2.1
Name: gene-outlier-detection
Version: 1.0
Summary: A Bayesian model for identifying gene expression outliers for individual single samples (N-of-1) when compared to a cohort of background datasets.
Author: John Vivian
Author-email: jtvivian@gmail.com
Requires-Python: >=3.6,<4.0
Classifier: Programming Language :: Python :: 3
Classifier: Programming Language :: Python :: 3.6
Classifier: Programming Language :: Python :: 3.7
Classifier: Programming Language :: Python :: 3.8
Requires-Dist: arviz (>=0.4.0,<0.5.0)
Requires-Dist: black (>=19.10b0,<20.0)
Requires-Dist: click (>=7.0,<8.0)
Requires-Dist: matplotlib (>=3.0,<4.0)
Requires-Dist: numpy (>=1.16,<2.0)
Requires-Dist: pandas (>=0.24.1,<0.25.0)
Requires-Dist: pymc3 (>=3.8,<4.0)
Requires-Dist: scipy (>=1.2,<2.0)
Requires-Dist: seaborn (>=0.9.0,<0.10.0)
Requires-Dist: sklearn (>=0.0.0,<0.0.1)
Requires-Dist: tables (>=3.5,<4.0)
Requires-Dist: theano (>=1.0.4,<2.0.0)
Requires-Dist: tqdm (>=4.31,<5.0)
